snaplib/__init__.py
snaplib/counter.py
snaplib/cross_validation.py
snaplib/dummied.py
snaplib/encoder.py
snaplib/feature_selection_bagged.py
snaplib/fit_pred_bagged.py
snaplib/nans.py
snaplib/recover.py
snaplib/save_load_algorithms.py
snaplib/snaplib.py
snaplib/splitter.py
snaplib-0.4.96.dist-info/LICENSE
snaplib-0.4.96.dist-info/METADATA
snaplib-0.4.96.dist-info/WHEEL
snaplib-0.4.96.dist-info/top_level.txt
snaplib-0.4.96.dist-info/RECORD
