Metadata-Version: 2.1
Name: snaplib
Version: 0.4.96
Summary: Data preprocessing lib
Home-page: https://github.com/kolasdevpy/snaplib
Author: Artsiom Kolas
Author-email: artyom.kolas@gmail.com
License: UNKNOWN
Platform: UNKNOWN
Classifier: Programming Language :: Python :: 3.7
Classifier: License :: OSI Approved :: GNU General Public License v3 (GPLv3)
License-File: LICENSE
Requires-Dist: pandas (>=1)
Requires-Dist: numpy (>=1)
